.bzrignore
README.txt
base.cfg
bootstrap.py
buildout.cfg
fabfile
install.cfg
setup.py
debian/changelog
debian/compat
debian/control
debian/copyright
debian/docs
debian/files
debian/pycompat
debian/rules
docs/CHANGES.txt
docs/INSTALLATION.txt
docs/UPGRADING.txt
examples/buildout-install/bootstrap.py
examples/buildout-install/buildout.cfg
examples/buildout-install/autobot/__init__.py
examples/buildout-install/autobot/settings.py
examples/buildout-install/etc/supervisord.conf
src/wheeljack/__init__.py
src/wheeljack/admin.py
src/wheeljack/builder.py
src/wheeljack/decorators.py
src/wheeljack/errors.py
src/wheeljack/feeds.py
src/wheeljack/forms.py
src/wheeljack/models.py
src/wheeljack/notification.py
src/wheeljack/repositories.py
src/wheeljack/scripts.py
src/wheeljack/testing.py
src/wheeljack/urls.py
src/wheeljack.egg-info/PKG-INFO
src/wheeljack.egg-info/SOURCES.txt
src/wheeljack.egg-info/dependency_links.txt
src/wheeljack.egg-info/entry_points.txt
src/wheeljack.egg-info/not-zip-safe
src/wheeljack.egg-info/requires.txt
src/wheeljack.egg-info/top_level.txt
src/wheeljack/migrations/0001_initial.py
src/wheeljack/migrations/0002_state_names.py
src/wheeljack/migrations/__init__.py
src/wheeljack/project/__init__.py
src/wheeljack/project/development.py
src/wheeljack/project/production.py
src/wheeljack/project/settings.py
src/wheeljack/project/urls.py
src/wheeljack/project/media/base.css
src/wheeljack/project/media/building.gif
src/wheeljack/project/media/jquery-1.2.6.min.js
src/wheeljack/project/media/wheeljack.js
src/wheeljack/project/templates/500.html
src/wheeljack/project/templates/base.html
src/wheeljack/project/templates/registration/logged_out.html
src/wheeljack/project/templates/registration/login.html
src/wheeljack/project/templates/registration/password_change_done.html
src/wheeljack/project/templates/registration/password_change_form.html
src/wheeljack/templates/feeds/buildlog_description.html
src/wheeljack/templates/feeds/buildlog_title.html
src/wheeljack/templates/wheeljack/mail_build_report.txt
src/wheeljack/templates/wheeljack/project_confirm_delete.html
src/wheeljack/templates/wheeljack/project_detail.html
src/wheeljack/templates/wheeljack/project_form.html
src/wheeljack/templates/wheeljack/project_list.html
