Metadata-Version: 1.0
Name: wheeljack
Version: 0.4
Summary: Wheeljack is a build system.
Home-page: https://launchpad.net/wheeljack
Author: Jeroen Vloothuis
Author-email: jeroen.vloothuis@xs4all.nl
License: UNKNOWN
Platform: UNKNOWN
Classifier: Development Status :: 3 - Alpha
Classifier: Programming Language :: Python
Classifier: Intended Audience :: Developers
Classifier: License :: OSI Approved :: BSD License
Classifier: Topic :: Software Development :: Build Tools
